<annotation>
	<folder>images</folder>
	<filename>N.b9210e2b-d8d1-11ec-91f9-f859718a6f1e.jpg</filename>
	<path>D:\AnacondaProjects\tez\Tensorflow\workspace\training\images\N.b9210e2b-d8d1-11ec-91f9-f859718a6f1e.jpg</path>
	<source>
		<database>Unknown</database>
	</source>
	<size>
		<width>640</width>
		<height>480</height>
		<depth>3</depth>
	</size>
	<segmented>0</segmented>
	<object>
		<name>N</name>
		<pose>Unspecified</pose>
		<truncated>0</truncated>
		<difficult>0</difficult>
		<bndbox>
			<xmin>231</xmin>
			<ymin>217</ymin>
			<xmax>406</xmax>
			<ymax>449</ymax>
		</bndbox>
	</object>
</annotation>
