<annotation>
	<folder>images</folder>
	<filename>S.59a1b1d2-d8d2-11ec-be88-f859718a6f1e.jpg</filename>
	<path>D:\AnacondaProjects\tez\Tensorflow\workspace\training\images\S.59a1b1d2-d8d2-11ec-be88-f859718a6f1e.jpg</path>
	<source>
		<database>Unknown</database>
	</source>
	<size>
		<width>640</width>
		<height>480</height>
		<depth>3</depth>
	</size>
	<segmented>0</segmented>
	<object>
		<name>S</name>
		<pose>Unspecified</pose>
		<truncated>0</truncated>
		<difficult>0</difficult>
		<bndbox>
			<xmin>197</xmin>
			<ymin>116</ymin>
			<xmax>413</xmax>
			<ymax>448</ymax>
		</bndbox>
	</object>
</annotation>
