<annotation>
	<folder>images</folder>
	<filename>U.8ac58525-d8d2-11ec-afb9-f859718a6f1e.jpg</filename>
	<path>D:\AnacondaProjects\tez\Tensorflow\workspace\training\images\U.8ac58525-d8d2-11ec-afb9-f859718a6f1e.jpg</path>
	<source>
		<database>Unknown</database>
	</source>
	<size>
		<width>640</width>
		<height>480</height>
		<depth>3</depth>
	</size>
	<segmented>0</segmented>
	<object>
		<name>U</name>
		<pose>Unspecified</pose>
		<truncated>0</truncated>
		<difficult>0</difficult>
		<bndbox>
			<xmin>83</xmin>
			<ymin>126</ymin>
			<xmax>281</xmax>
			<ymax>319</ymax>
		</bndbox>
	</object>
</annotation>
